pp/__init__.py
pp/model.py
pp/regression.py
pp/spectral.py
pp/statistics.py
pp/core/__init__.py
pp/core/maximizers.py
pp/core/weights_producers.py
pp/core/distributions/__init__.py
pp/core/distributions/inverse_gaussian.py
point_process-0.2.dist-info/LICENSE
point_process-0.2.dist-info/METADATA
point_process-0.2.dist-info/WHEEL
point_process-0.2.dist-info/top_level.txt
point_process-0.2.dist-info/RECORD
