Metadata-Version: 2.1
Name: point-process
Version: 0.2
Summary: UNKNOWN
Home-page: UNKNOWN
Author: Andrea Bonvini
Author-email: a.bonvini96@gmail.com
License: UNKNOWN
Platform: UNKNOWN
Requires-Dist: certifi (==2020.6.20)
Requires-Dist: cycler (==0.10.0)
Requires-Dist: kiwisolver (==1.3.1)
Requires-Dist: matplotlib (==3.3.2)
Requires-Dist: numpy (==1.19.4)
Requires-Dist: pandas (==1.1.4)
Requires-Dist: pillow (==8.0.1)
Requires-Dist: pyparsing (==2.4.7)
Requires-Dist: python-dateutil (==2.8.1)
Requires-Dist: pytz (==2020.4)
Requires-Dist: scipy (==1.5.4)
Requires-Dist: six (==1.15.0)
